verilog/rtl/asyn_dff.v
module asyn_dff # (
    parameter WIDTH = 8 ) 
(
    input wire clk,
    input wire rst_n,
    input [WIDTH-1:0] data_in,
    output reg [WIDTH-1:0] data_out
);
    // DFF with asynchronous rst_n, 
    always @ (posedge clk or negedge rst_n) begin
        if (!rst_n) begin
            data_out <= 0;
        end
        else begin
            data_out <= data_in;
        end
     end
endmodule

verilog/rtl/adder.v
module adder(
    input wire [7:0] data,
    input wire [11:0] psum,
    output wire [11:0] new_psum
);
    wire [11:0] data_sign_extended;
    assign data_sign_extended = {{4{data[7]}}, data};
    // new_psum = psum + sign_extended(data)
    assign new_psum = data_sign_extended + psum; 
endmodule

verilog/rtl/comparator.v
module comparator(
    input wire [7:0] a,
    input wire [7:0] b,
    output wire [7:0] out
);
    // wire [7:0] sub;
    // assign sub = a + ~b + 1'b1;
    // // out = (a > b) ? a : b
    // assign out = (a[7] != b[7]) ? (a[7] ? b : a) : (sub[7] ? b : a); 
    wire ctrl;
    assign out = ctrl ? a : b;

    assign ctrl = (a[7] != b[7]) ? b[7] : ((a[6:0] > b[6:0]) ? 1'b1 : 1'b0);
endmodule

verilog/rtl/MandS.v
module MandS(
    input wire clk,
    input wire resetb,
    input wire start,
    input wire valid,
    input wire [7:0] data,  // signed, 2'complement
    output wire [7:0] Max,
    output wire [11:0] Sum
);
    // internal signal
    wire [7:0] valid_new_pmax; 
    wire [11:0] valid_new_psum;
    wire [7:0] valid_max_data; 
    wire [7:0] valid_sum_data; 
    wire [7:0] pmax;
    wire [7:0] new_pmax;
    wire [11:0] psum;
    wire [11:0] new_psum;

    // output
    assign Max = pmax;
    assign Sum = psum;

    assign valid_max_data = valid ? data : 8'b10000000;
    assign valid_sum_data = valid ? data : 8'b0;

    assign valid_new_pmax = start ? 8'b10000000 : new_pmax;
    assign valid_new_psum = start ? 12'b0 : new_psum;

    // comparator
    comparator u_comparator(
        .a(valid_max_data),
        .b(pmax),
        .out(new_pmax)
    );

    // Max (output) register
    asyn_dff #(8) u_max_reg(
        .clk(clk),
        .rst_n(resetb),
        .data_in(valid_new_pmax),
        .data_out(pmax)
    );

    // adder
    adder u_adder(
        .data(valid_sum_data),
        .psum(psum),
        .new_psum(new_psum)
    );

    // Sum (output) register
    asyn_dff #(12) u_sum_reg(
        .clk(clk),
        .rst_n(resetb),
        .data_in(valid_new_psum),
        .data_out(psum)
    );
endmodule

verilog/tb/MandS_tb.v
`timescale 1ns / 1ps

module MandS_tb();
    reg clk;
    reg resetb;
    reg start;
    reg valid;
    reg [7:0] data;
    wire [7:0] Max;
    wire [11:0] Sum;

    // generate clk
    always #10 clk = ~clk;

    initial begin
        clk = 1'b1;
        resetb = 1'b0;
        start = 1'b0;
        valid = 1'b0;
        data = 8'b0;
        $display("test running...");
        #40 resetb = 1'b1;
        #20 start = 1'b1;
        #20 start = 1'b0;
            valid = 1'b1;
            data = -5;
        #20 data = -2;
        #20 data = 8'd3;
        #20 data = 8'd1;
        #20 data = 8'd7;
        #20 data = 8'd0;
        #20 data = 8'd1;
        #20 data = -5;
        #20 data = 8'd3;
        #20 valid = 1'b0;
        #60 start = 1'b1;
        #20 start = 1'b0;
            valid = 1'b1;
            data = -1;
        #20 data = 8'd5;
        #20 data = 8'd233;
        #20 valid = 1'b0;
        #50 resetb = 1'b0;
        #40 $finish;
    end


    initial begin
        $dumpfile("sim/dumpfile/wave.vcd");
		$dumpvars(0,MandS_tb);
	end

    MandS u_MandS(
        .clk(clk),
        .resetb(resetb),
        .start(start),
        .valid(valid),
        .data(data),
        .Max(Max),
        .Sum(Sum)
    );
endmodule

verilog/sim/dumpfile/wave.vcd
$date
	Sun Mar 24 00:42:07 2024
$end
$version
	Icarus Verilog
$end
$timescale
	1ps
$end
$scope module MandS_tb $end
$var wire 12 ! Sum [11:0] $end
$var wire 8 " Max [7:0] $end
$var reg 1 # clk $end
$var reg 8 $ data [7:0] $end
$var reg 1 % resetb $end
$var reg 1 & start $end
$var reg 1 ' valid $end
$scope module u_MandS $end
$var wire 8 ( Max [7:0] $end
$var wire 12 ) Sum [11:0] $end
$var wire 1 # clk $end
$var wire 8 * data [7:0] $end
$var wire 1 % resetb $end
$var wire 1 & start $end
$var wire 1 ' valid $end
$var wire 8 + valid_sum_data [7:0] $end
$var wire 12 , valid_new_psum [11:0] $end
$var wire 8 - valid_new_pmax [7:0] $end
$var wire 8 . valid_max_data [7:0] $end
$var wire 12 / psum [11:0] $end
$var wire 8 0 pmax [7:0] $end
$var wire 12 1 new_psum [11:0] $end
$var wire 8 2 new_pmax [7:0] $end
$scope module u_adder $end
$var wire 8 3 data [7:0] $end
$var wire 12 4 psum [11:0] $end
$var wire 12 5 new_psum [11:0] $end
$var wire 12 6 data_sign_extended [11:0] $end
$upscope $end
$scope module u_comparator $end
$var wire 8 7 a [7:0] $end
$var wire 8 8 out [7:0] $end
$var wire 1 9 ctrl $end
$var wire 8 : b [7:0] $end
$upscope $end
$scope module u_max_reg $end
$var wire 1 # clk $end
$var wire 8 ; data_in [7:0] $end
$var wire 1 % rst_n $end
$var reg 8 < data_out [7:0] $end
$upscope $end
$scope module u_sum_reg $end
$var wire 1 # clk $end
$var wire 12 = data_in [11:0] $end
$var wire 1 % rst_n $end
$var reg 12 > data_out [11:0] $end
$upscope $end
$upscope $end
$upscope $end
$enddefinitions $end
#0
$dumpvars
b0 >
b0 =
b0 <
b0 ;
b0 :
09
b0 8
b10000000 7
b0 6
b0 5
b0 4
b0 3
b0 2
b0 1
b0 0
b0 /
b10000000 .
b0 -
b0 ,
b0 +
b0 *
b0 )
b0 (
0'
0&
0%
b0 $
1#
b0 "
b0 !
$end
#10000
0#
#20000
1#
#30000
0#
#40000
1#
1%
#50000
0#
#60000
b10000000 2
b10000000 8
b10000000 "
b10000000 (
b10000000 0
b10000000 :
b10000000 <
b10000000 -
b10000000 ;
1#
1&
#70000
0#
#80000
b11111011 -
b11111011 ;
b11111011 2
b11111011 8
19
b111111111011 ,
b111111111011 =
b11111011 .
b11111011 7
b111111111011 1
b111111111011 5
b111111111011 6
b11111011 +
b11111011 3
1#
b11111011 $
b11111011 *
1'
0&
#90000
0#
#100000
b111111111011 !
b111111111011 )
b111111111011 /
b111111111011 4
b111111111011 >
b11111011 "
b11111011 (
b11111011 0
b11111011 :
b11111011 <
b11111110 -
b11111110 ;
b11111110 2
b11111110 8
b111111111001 ,
b111111111001 =
b11111110 .
b11111110 7
b111111111001 1
b111111111001 5
b111111111110 6
b11111110 +
b11111110 3
1#
b11111110 $
b11111110 *
#110000
0#
#120000
b11111110 "
b11111110 (
b11111110 0
b11111110 :
b11111110 <
b111111111001 !
b111111111001 )
b111111111001 /
b111111111001 4
b111111111001 >
b11 -
b11 ;
b11 2
b11 8
b111111111100 ,
b111111111100 =
b11 .
b11 7
b111111111100 1
b111111111100 5
b11 6
b11 +
b11 3
1#
b11 $
b11 *
#130000
0#
#140000
09
b111111111100 !
b111111111100 )
b111111111100 /
b111111111100 4
b111111111100 >
b11 "
b11 (
b11 0
b11 :
b11 <
b11 -
b11 ;
b11 2
b11 8
b111111111101 ,
b111111111101 =
b1 .
b1 7
b111111111101 1
b111111111101 5
b1 6
b1 +
b1 3
1#
b1 $
b1 *
#150000
0#
#160000
b111111111101 !
b111111111101 )
b111111111101 /
b111111111101 4
b111111111101 >
b111 -
b111 ;
b111 2
b111 8
19
b100 ,
b100 =
b111 .
b111 7
b100 1
b100 5
b111 6
b111 +
b111 3
1#
b111 $
b111 *
#170000
0#
#180000
b100 !
b100 )
b100 /
b100 4
b100 >
b111 "
b111 (
b111 0
b111 :
b111 <
09
b111 -
b111 ;
b111 2
b111 8
b100 ,
b100 =
b0 .
b0 7
b100 1
b100 5
b0 6
b0 +
b0 3
1#
b0 $
b0 *
#190000
0#
#200000
b101 ,
b101 =
b1 .
b1 7
b101 1
b101 5
b1 6
b1 +
b1 3
1#
b1 $
b1 *
#210000
0#
#220000
b101 !
b101 )
b101 /
b101 4
b101 >
b0 ,
b0 =
b11111011 .
b11111011 7
b0 1
b0 5
b111111111011 6
b11111011 +
b11111011 3
1#
b11111011 $
b11111011 *
#230000
0#
#240000
b0 !
b0 )
b0 /
b0 4
b0 >
b11 ,
b11 =
b11 .
b11 7
b11 1
b11 5
b11 6
b11 +
b11 3
1#
b11 $
b11 *
#250000
0#
#260000
b11 !
b11 )
b11 /
b11 4
b11 >
b11 ,
b11 =
b10000000 .
b10000000 7
b11 1
b11 5
b0 6
b0 +
b0 3
1#
0'
#270000
0#
#280000
1#
#290000
0#
#300000
1#
#310000
0#
#320000
b10000000 2
b10000000 8
b10000000 "
b10000000 (
b10000000 0
b10000000 :
b10000000 <
b0 1
b0 5
b0 !
b0 )
b0 /
b0 4
b0 >
b10000000 -
b10000000 ;
b0 ,
b0 =
1#
1&
#330000
0#
#340000
b11111111 -
b11111111 ;
b11111111 2
b11111111 8
19
b111111111111 ,
b111111111111 =
b11111111 .
b11111111 7
b111111111111 1
b111111111111 5
b111111111111 6
b11111111 +
b11111111 3
1#
b11111111 $
b11111111 *
1'
0&
#350000
0#
#360000
b11111111 "
b11111111 (
b11111111 0
b11111111 :
b11111111 <
b111111111111 !
b111111111111 )
b111111111111 /
b111111111111 4
b111111111111 >
b101 -
b101 ;
b101 2
b101 8
b100 ,
b100 =
b101 .
b101 7
b100 1
b100 5
b101 6
b101 +
b101 3
1#
b101 $
b101 *
#370000
0#
#380000
b100 !
b100 )
b100 /
b100 4
b100 >
b101 "
b101 (
b101 0
b101 :
b101 <
09
b101 -
b101 ;
b101 2
b101 8
b111111101101 ,
b111111101101 =
b11101001 .
b11101001 7
b111111101101 1
b111111101101 5
b111111101001 6
b11101001 +
b11101001 3
1#
b11101001 $
b11101001 *
#390000
0#
#400000
b111111101101 !
b111111101101 )
b111111101101 /
b111111101101 4
b111111101101 >
b111111101101 ,
b111111101101 =
b10000000 .
b10000000 7
b111111101101 1
b111111101101 5
b0 6
b0 +
b0 3
1#
0'
#410000
0#
#420000
1#
#430000
0#
#440000
1#
#450000
b0 -
b0 ;
b0 ,
b0 =
b0 2
b0 8
b0 1
b0 5
b0 !
b0 )
b0 /
b0 4
b0 >
b0 "
b0 (
b0 0
b0 :
b0 <
0#
0%
